sales_report.py
sales_report_tikhonmakeev-0.1.dist-info/METADATA
sales_report_tikhonmakeev-0.1.dist-info/WHEEL
sales_report_tikhonmakeev-0.1.dist-info/entry_points.txt
sales_report_tikhonmakeev-0.1.dist-info/top_level.txt
sales_report_tikhonmakeev-0.1.dist-info/RECORD
